persona_ai/__init__.py
persona_ai/code_runners/__init__.py
persona_ai/code_runners/base.py
persona_ai/code_runners/local.py
persona_ai/constants.py
persona_ai/conversation_listeners/__init__.py
persona_ai/conversation_listeners/terminal_conversation_listener.py
persona_ai/conversations/__init__.py
persona_ai/conversations/manager.py
persona_ai/domain/__init__.py
persona_ai/domain/conversations.py
persona_ai/domain/events.py
persona_ai/domain/repositories.py
persona_ai/domain/roles.py
persona_ai/domain/schemas/__init__.py
persona_ai/domain/schemas/crud.py
persona_ai/domain/tasks.py
persona_ai/domain/utils.py
persona_ai/infrastructure/__init__.py
persona_ai/infrastructure/repositories/__init__.py
persona_ai/infrastructure/repositories/base.py
persona_ai/infrastructure/repositories/in_memory.py
persona_ai/infrastructure/repositories/mongo.py
persona_ai/initializers/__init__.py
persona_ai/initializers/env_configurator.py
persona_ai/initializers/persona_configuration.py
persona_ai/models/__init__.py
persona_ai/models/base.py
persona_ai/models/code_bison.py
persona_ai/models/gemini.py
persona_ai/models/text_bison.py
persona_ai/moderation/__init__.py
persona_ai/moderation/ai_moderator.py
persona_ai/moderation/base.py
persona_ai/moderation/history_moderator.py
persona_ai/moderation/history_moderator_fc_system_instructions.py
persona_ai/moderation/history_moderator_no_fc.py
persona_ai/moderation/react_moderator.py
persona_ai/personas/__init__.py
persona_ai/personas/agent.py
persona_ai/personas/assistant.py
persona_ai/personas/base.py
persona_ai/personas/coder.py
persona_ai/personas/party.py
persona_ai/personas/technician.py
persona_ai/personas/terminal.py
persona_ai/prompt_templates/agent.jinja2
persona_ai/prompt_templates/assistant.jinja2
persona_ai/prompt_templates/coder.jinja2
persona_ai/prompt_templates/history_moderator.jinja2
persona_ai/prompt_templates/history_moderator_fc_prompt.jinja2
persona_ai/prompt_templates/history_moderator_fc_system_instructions.jinja2
persona_ai-0.1.16.dist-info/METADATA
persona_ai-0.1.16.dist-info/WHEEL
persona_ai-0.1.16.dist-info/RECORD
