Metadata-Version: 2.1
Name: persona_ai
Version: 0.1.16
Summary: Persona is a groundbreaking distributed AI agent system utilizing Google Vertex AI's premier Large Language Models such as Gemini-pro, Text-Bison, and Code-Bison. Developed by Applica Software Guru, Persona is engineered for scalable, high-performance, and intelligent operations across various data sets and applications. It harnesses the power of Google's Vertex AI to deliver unmatched insights and automation capabilities, setting new standards in AI-driven analytics and decision-making
License: MIT
Author: Bruno Fortunato
Author-email: bruno.fortunato@applica.guru
Requires-Python: >=3.10,<4.0
Classifier: License :: OSI Approved :: MIT License
Classifier: Programming Language :: Python :: 3
Classifier: Programming Language :: Python :: 3.10
Classifier: Programming Language :: Python :: 3.11
Classifier: Programming Language :: Python :: 3.12
Requires-Dist: Jinja2 (>=3.1.3,<4.0.0)
Requires-Dist: google-api-python-client (>=2.125.0,<3.0.0)
Requires-Dist: google-cloud-aiplatform (>=1.47.0,<2.0.0)
Requires-Dist: pika (>=1.3.2,<2.0.0)
Requires-Dist: pycryptodome (>=3.20.0,<4.0.0)
Requires-Dist: pydantic (>=2.6.4,<3.0.0)
Requires-Dist: pymongo (>=4.6.3,<5.0.0)
Requires-Dist: python-dotenv (>=1.0.1,<2.0.0)
Requires-Dist: pywhatkit (>=5.4,<6.0)
Requires-Dist: shortuuid (>=1.0.13,<2.0.0)
Requires-Dist: strip-markdown (>=1.3,<2.0)
Requires-Dist: termcolor (>=2.4.0,<3.0.0)
